encryptfile/__init__.py
encryptfile/__main__.py
encryptfile/encryptfile.py
tests/__init__.py
tests/conftest.py
tests/encryptfile/__init__.py
tests/encryptfile/test_encryptfile.py
encrypt_file-2.1.dist-info/LICENSE
encrypt_file-2.1.dist-info/METADATA
encrypt_file-2.1.dist-info/WHEEL
encrypt_file-2.1.dist-info/entry_points.txt
encrypt_file-2.1.dist-info/top_level.txt
encrypt_file-2.1.dist-info/RECORD
