Metadata-Version: 2.1
Name: encrypt-file
Version: 2.1
Summary: CLI to encrypt or decrypt files with ONLY ONE COMAND
Home-page: https://github.com/brunocampos01/encrypt-file
Author: Bruno Campos
Author-email: brunocampos01@gmail.com
License: MIT
Keywords: encrypt,decrypt,cli,easy,file
Platform: any
Classifier: Programming Language :: Python
Classifier: Natural Language :: English
Classifier: License :: OSI Approved :: MIT License
License-File: LICENSE
Requires-Dist: cryptography (==2.8)
Requires-Dist: humanfriendly (==10.0)
Requires-Dist: idna (==2.8)
Requires-Dist: pycparser (==2.21)
Requires-Dist: pyfiglet (==0.8.post1)
Requires-Dist: six (==1.16.0)
Requires-Dist: sty (==1.0.0b12)
